README.rst
requirements_linux.txt
requirements_macOS.txt
setup.py
cocoricofm/__init__.py
cocoricofm/__main__.py
cocoricofm/controller.py
cocoricofm/denon.py
cocoricofm/growl_notify.py
cocoricofm/growl_server.py
cocoricofm/httpclient.py
cocoricofm/keyboard_input.py
cocoricofm/linux_notify.py
cocoricofm/lirc_input.py
cocoricofm/main.py
cocoricofm/osx_notify.py
cocoricofm/player.py
cocoricofm/pylast.py
cocoricofm/radios.py
cocoricofm/tagger.py
cocoricofm/ui.py
cocoricofm/web_remote.py
cocoricofm.egg-info/PKG-INFO
cocoricofm.egg-info/SOURCES.txt
cocoricofm.egg-info/dependency_links.txt
cocoricofm.egg-info/entry_points.txt
cocoricofm.egg-info/requires.txt
cocoricofm.egg-info/top_level.txt
cocoricofm/playlistparser/__init__.py
cocoricofm/playlistparser/plparser/__init__.py
cocoricofm/playlistparser/plparser/common.py
cocoricofm/playlistparser/plparser/m3uparser.py
cocoricofm/playlistparser/plparser/plsparser.py
cocoricofm/playlistparser/plparser/xmlparser.py
cocoricofm/playlistparser/plparser/xspfparser.py
cocoricofm/static/no-cover.png
cocoricofm/static/viz.js
cocoricofm/templates/index.html
cocoricofm/templates/layout.html
cocoricofm/templates/pipeline.html
data/RaspberryPiHowTo.rst
data/cocoricofm.cfg.sample
data/cocoricofm.service
data/gen_pylast_md5sum.py
data/growl.service
data/screenshot.png
data/streamzap.lirc