Metadata-Version: 1.1
Name: cocoricofm
Version: 1.4
Summary: A little radio player
Home-page: https://gitlab.com/philn/CocoRicoFM/
Author: Philippe Normand
Author-email: phil@base-art.net
License: GPL3
Keywords: radio,multimedia,gstreamer,recording,gtk+,libre.fm,last.fm
Platform: UNKNOWN
Classifier: Development Status :: 5 - Production/Stable
Classifier: Environment :: Console
Classifier: Environment :: MacOS X
Classifier: Environment :: Web Environment
Classifier: Environment :: X11 Applications :: GTK
Classifier: Framework :: AsyncIO
Classifier: Operating System :: OS Independent
Classifier: Programming Language :: Python :: 3.6
Classifier: Topic :: Multimedia :: Sound/Audio :: Players
Classifier: Intended Audience :: End Users/Desktop
Classifier: License :: OSI Approved :: GNU General Public License v3 (GPLv3)
